controller.py
job.py
main_cobol_convert.py
unit.py
base/__init__.py
base/cobol_java_field.py
base/cobol_to_java_base.py
base/cobol_util.py
base/get_file_encoding.py
base/java_code_builder.py
base/make_cst_java.py
base/parsing_cobol.py
field_change_java/__init__.py
field_change_java/method_field_change.py
jobs/__init__.py
jobs/job_000.py
jobs/job_001.py
jobs/job_002.py
jobs/job_0024.py
jobs/job_0025.py
jobs/job_0026.py
jobs/job_003.py
jobs/job_004.py
jobs/job_005.py
merge_copy/__init__.py
merge_copy/merge_copy_file.py
parsing_data_division/__init__.py
parsing_data_division/parsing_data_division.py
pilot_sample_linkstec-0.0.1.dist-info/licenses/LICENSE
processors/__init__.py
processors/merge_continuation_lines.py
processors/remove_comment_lines.py
processors/replace_with_todo.py
processors/trim_leading_chars_to_spaces.py
splitters/__init__.py
splitters/cobol_splitter.py
pilot_sample_linkstec-0.0.1.dist-info/METADATA
pilot_sample_linkstec-0.0.1.dist-info/WHEEL
pilot_sample_linkstec-0.0.1.dist-info/top_level.txt
pilot_sample_linkstec-0.0.1.dist-info/RECORD
