Metadata-Version: 2.4
Name: pilot.sample.linkstec
Version: 0.0.1
Summary: pilot of the ship, a tool for managing and deploying Python projects.
Author-email: wanglr <wanglr1980@gmail.com>
License-Expression: MIT
Project-URL: Homepage, https://github.com/nighter1980/pilotsample
Project-URL: Issues, https://github.com/nighter1980/pilotsample/issues
Keywords: python,project management,deployment
Classifier: Programming Language :: Python :: 3
Classifier: Operating System :: OS Independent
Requires-Python: >=3.9
License-File: LICENSE
Dynamic: license-file
